precipitation/FACETA.py
precipitation/__init__.py
precipitation/__version__.py
precipitation/geo_tools.py
precipitation/h5py_tools.py
precipitation/hidro_tools.py
precipitation/libraries.py
hidro_UNC_joaquin.segura.ellis-0.1.10.1.dist-info/LICENSE
hidro_UNC_joaquin.segura.ellis-0.1.10.1.dist-info/METADATA
hidro_UNC_joaquin.segura.ellis-0.1.10.1.dist-info/WHEEL
hidro_UNC_joaquin.segura.ellis-0.1.10.1.dist-info/top_level.txt
hidro_UNC_joaquin.segura.ellis-0.1.10.1.dist-info/RECORD
