Metadata-Version: 2.1
Name: hidro-UNC-joaquin.segura.ellis
Version: 0.1.10.1
Summary: Tools for analize precipitation data for hydraulic design.
Home-page: https://github.com/JoaquinSeguElli/hidro-UNC
Author: Joaquin Sebastian Segura Ellis
Author-email: joaquin.segura.ellis@mi.unc.edu.ar
Project-URL: Bug Tracker, https://github.com/JoaquinSeguElli/hidro-UNC/issues
Classifier: Natural Language :: English
Classifier: Programming Language :: Python :: 3
Classifier: License :: OSI Approved :: MIT License
Classifier: Operating System :: Microsoft :: Windows :: Windows 10
Classifier: Operating System :: Microsoft :: Windows :: Windows 11
Classifier: Development Status :: 1 - Planning
Classifier: Intended Audience :: Science/Research
Classifier: Topic :: Scientific/Engineering :: Hydrology
Requires-Python: >=3.6
License-File: LICENSE
